CHANGES.rst
COPYING.txt
MANIFEST.in
README.txt
setup.cfg
setup.py
rattail_cognitive/__init__.py
rattail_cognitive/_version.py
rattail_cognitive/labels.py
rattail_cognitive.egg-info/PKG-INFO
rattail_cognitive.egg-info/SOURCES.txt
rattail_cognitive.egg-info/dependency_links.txt
rattail_cognitive.egg-info/not-zip-safe
rattail_cognitive.egg-info/requires.txt
rattail_cognitive.egg-info/top_level.txt